README.txt
setup.py
collective/__init__.py
collective.deepsitemap.egg-info/PKG-INFO
collective.deepsitemap.egg-info/SOURCES.txt
collective.deepsitemap.egg-info/dependency_links.txt
collective.deepsitemap.egg-info/entry_points.txt
collective.deepsitemap.egg-info/namespace_packages.txt
collective.deepsitemap.egg-info/not-zip-safe
collective.deepsitemap.egg-info/paster_plugins.txt
collective.deepsitemap.egg-info/requires.txt
collective.deepsitemap.egg-info/top_level.txt
collective/deepsitemap/__init__.py
collective/deepsitemap/configure.zcml
collective/deepsitemap/navigation.py
collective/deepsitemap/permissions.py
collective/deepsitemap/tests.py
collective/deepsitemap/profiles/default/metadata.xml
collective/deepsitemap/profiles/default/rolemap.xml
docs/HISTORY.txt
docs/INSTALL.txt
docs/LICENSE.GPL
docs/LICENSE.txt