Metadata-Version: 1.0
Name: collective.deepsitemap
Version: 1.0a
Summary: A sitemap replacement for Plone, whose depth is configurable per request.
Home-page: http://svn.plone.org/svn/collective/collective.deepsitemap/
Author: RedTurtle Technology
Author-email: sviluppoplone@redturtle.net
License: GPL
Platform: UNKNOWN
Classifier: Framework :: Plone
Classifier: Programming Language :: Python
Classifier: Development Status :: 3 - Alpha
